{"chunk_definitions":[{"row":19,"row_count":1,"visible":true,"expansion_state":0,"options":{"engine":"r","label":"recordar vectorizacion","echo":true},"document_id":"6F13E55F","chunk_id":"cz2mp9r1kkhmy","chunk_label":"recordar vectorizacion"},{"row":83,"row_count":1,"visible":true,"expansion_state":0,"options":{"engine":"r","echo":true,"label":"unnamed-chunk-343"},"document_id":"6F13E55F","chunk_id":"cb01y6ew4ldxd","chunk_label":"unnamed-chunk-2"},{"row":100,"row_count":1,"visible":true,"expansion_state":0,"options":{"engine":"r","echo":true,"label":"unnamed-chunk-344"},"document_id":"6F13E55F","chunk_id":"cb42t8gpl7upu","chunk_label":"unnamed-chunk-3"},{"row":107,"row_count":1,"visible":true,"expansion_state":0,"options":{"engine":"r","echo":true,"label":"unnamed-chunk-345"},"document_id":"6F13E55F","chunk_id":"clok24s7laxqc","chunk_label":"unnamed-chunk-4"},{"row":115,"row_count":1,"visible":true,"expansion_state":0,"options":{"engine":"r","echo":true,"label":"unnamed-chunk-346"},"document_id":"6F13E55F","chunk_id":"cnq9jncacs0vn","chunk_label":"unnamed-chunk-5"},{"row":123,"row_count":1,"visible":true,"expansion_state":0,"options":{"engine":"r","label":"unnamed-chunk-342"},"document_id":"6F13E55F","chunk_id":"ct54vkvhw1slq","chunk_label":"unnamed-chunk-6"},{"row":130,"row_count":1,"visible":true,"expansion_state":0,"options":{"engine":"r","echo":true,"label":"unnamed-chunk-347"},"document_id":"6F13E55F","chunk_id":"c75qvhm2qy8m7","chunk_label":"unnamed-chunk-7"},{"row":146,"row_count":1,"visible":true,"expansion_state":0,"options":{"engine":"r","echo":true,"label":"unnamed-chunk-348"},"document_id":"6F13E55F","chunk_id":"cnda6xxx9dryo","chunk_label":"unnamed-chunk-8"},{"row":151,"row_count":1,"visible":true,"expansion_state":0,"options":{"engine":"r","echo":true,"label":"unnamed-chunk-349"},"document_id":"6F13E55F","chunk_id":"c97r9v0747lny","chunk_label":"unnamed-chunk-9"},{"row":163,"row_count":1,"visible":true,"expansion_state":0,"options":{"engine":"r","echo":true,"label":"unnamed-chunk-350"},"document_id":"6F13E55F","chunk_id":"curw02eliyaze","chunk_label":"unnamed-chunk-10"},{"row":195,"row_count":1,"visible":true,"expansion_state":0,"options":{"engine":"r","echo":true,"label":"unnamed-chunk-351"},"document_id":"6F13E55F","chunk_id":"c1o6gqsfaknh7","chunk_label":"unnamed-chunk-12"},{"row":200,"row_count":1,"visible":true,"expansion_state":0,"options":{"engine":"r","echo":true,"error":true,"label":"unnamed-chunk-352"},"document_id":"6F13E55F","chunk_id":"cli8q6qceuet2","chunk_label":"unnamed-chunk-13"},{"row":212,"row_count":1,"visible":true,"expansion_state":0,"options":{"engine":"r","echo":true,"label":"unnamed-chunk-353"},"document_id":"6F13E55F","chunk_id":"ckn1kecrou0w1","chunk_label":"unnamed-chunk-14"},{"row":219,"row_count":1,"visible":true,"expansion_state":0,"options":{"engine":"r","echo":true,"label":"unnamed-chunk-354"},"document_id":"6F13E55F","chunk_id":"ca72vrzya7m40","chunk_label":"unnamed-chunk-15"},{"row":231,"row_count":1,"visible":true,"expansion_state":0,"options":{"engine":"r","echo":true,"label":"unnamed-chunk-355"},"document_id":"6F13E55F","chunk_id":"cb0rm567pkatv","chunk_label":"unnamed-chunk-16"},{"row":238,"row_count":1,"visible":true,"expansion_state":0,"options":{"engine":"r","echo":true,"label":"unnamed-chunk-356"},"document_id":"6F13E55F","chunk_id":"c74cc7yg8dkvi","chunk_label":"unnamed-chunk-17"},{"row":279,"row_count":1,"visible":true,"expansion_state":0,"options":{"engine":"r","echo":true,"label":"unnamed-chunk-357"},"document_id":"6F13E55F","chunk_id":"cj8n4qgvikque","chunk_label":"unnamed-chunk-19"},{"row":284,"row_count":1,"visible":true,"expansion_state":0,"options":{"engine":"r","echo":true,"label":"unnamed-chunk-358"},"document_id":"6F13E55F","chunk_id":"cwqmnakzs9xog","chunk_label":"unnamed-chunk-20"},{"row":295,"row_count":1,"visible":true,"expansion_state":0,"options":{"engine":"r","echo":true,"label":"unnamed-chunk-359"},"document_id":"6F13E55F","chunk_id":"cnwhicgoey9b2","chunk_label":"unnamed-chunk-21"},{"row":302,"row_count":1,"visible":true,"expansion_state":0,"options":{"engine":"r","echo":true,"label":"unnamed-chunk-360"},"document_id":"6F13E55F","chunk_id":"cj4izgm6gw08r","chunk_label":"unnamed-chunk-22"},{"row":312,"row_count":1,"visible":true,"expansion_state":0,"options":{"engine":"r","echo":true,"label":"unnamed-chunk-361"},"document_id":"6F13E55F","chunk_id":"c7y6el0j5sf5z","chunk_label":"unnamed-chunk-23"},{"row":317,"row_count":1,"visible":true,"expansion_state":0,"options":{"engine":"r","label":"unnamed-chunk-362"},"document_id":"6F13E55F","chunk_id":"ck7nvoyvv6nnx","chunk_label":"unnamed-chunk-24"},{"row":322,"row_count":1,"visible":true,"expansion_state":0,"options":{"engine":"r","echo":true,"label":"unnamed-chunk-363"},"document_id":"6F13E55F","chunk_id":"crysnglfp8cu8","chunk_label":"unnamed-chunk-25"},{"row":329,"row_count":1,"visible":true,"expansion_state":0,"options":{"engine":"r","echo":true,"label":"unnamed-chunk-364"},"document_id":"6F13E55F","chunk_id":"cz45tdrfrr9ag","chunk_label":"unnamed-chunk-26"},{"row":338,"row_count":1,"visible":true,"expansion_state":0,"options":{"engine":"r","echo":true,"label":"unnamed-chunk-365"},"document_id":"6F13E55F","chunk_id":"cbu9yswzcm8dr","chunk_label":"unnamed-chunk-27"},{"row":357,"row_count":1,"visible":true,"expansion_state":0,"options":{"engine":"r","echo":true,"label":"unnamed-chunk-366"},"document_id":"6F13E55F","chunk_id":"cftbay55m82ue","chunk_label":"unnamed-chunk-28"},{"row":366,"row_count":1,"visible":true,"expansion_state":0,"options":{"engine":"r","echo":true,"label":"unnamed-chunk-367"},"document_id":"6F13E55F","chunk_id":"ctk5a2ev0rgvz","chunk_label":"unnamed-chunk-29"},{"row":373,"row_count":1,"visible":true,"expansion_state":0,"options":{"engine":"r","echo":true,"label":"unnamed-chunk-368"},"document_id":"6F13E55F","chunk_id":"c5pvzblf9fxn6","chunk_label":"unnamed-chunk-30"},{"row":387,"row_count":1,"visible":true,"expansion_state":0,"options":{"engine":"r","echo":true,"label":"unnamed-chunk-369"},"document_id":"6F13E55F","chunk_id":"cs0cuaw0j58m7","chunk_label":"unnamed-chunk-31"},{"row":412,"row_count":1,"visible":true,"expansion_state":0,"options":{"engine":"r","echo":true,"label":"unnamed-chunk-370"},"document_id":"6F13E55F","chunk_id":"cip97rku9minu","chunk_label":"unnamed-chunk-32"},{"row":421,"row_count":1,"visible":true,"expansion_state":0,"options":{"engine":"r","echo":true,"label":"unnamed-chunk-371"},"document_id":"6F13E55F","chunk_id":"ce5iy5wuq2d51","chunk_label":"unnamed-chunk-33"},{"row":428,"row_count":1,"visible":true,"expansion_state":0,"options":{"engine":"r","echo":true,"label":"unnamed-chunk-372"},"document_id":"6F13E55F","chunk_id":"caa27jcja88kb","chunk_label":"unnamed-chunk-34"},{"row":439,"row_count":1,"visible":true,"expansion_state":0,"options":{"engine":"r","echo":true,"label":"unnamed-chunk-373"},"document_id":"6F13E55F","chunk_id":"cpnqa7laceqgd","chunk_label":"unnamed-chunk-35"}],"doc_write_time":1541481212}